custom_colormaps/__init__.py
custom_colormaps/colordata/cmapdata.toml
custom_colormaps/main.py
custom_colormaps/return_colormap.py
custom_colormaps-0.3.6.dist-info/LICENSE
custom_colormaps-0.3.6.dist-info/WHEEL
custom_colormaps-0.3.6.dist-info/METADATA
custom_colormaps-0.3.6.dist-info/RECORD
