Metadata-Version: 2.1
Name: custom-colormaps
Version: 0.3.6
Summary: custom colormaps 
Home-page: https://github.com/a-lab-nagoya/custom-colormaps
License: MIT
Author: Rin Yamada
Author-email: yamada@a.phys.nagoya-u.ac.jp
Requires-Python: >=3.6,<4.0
Classifier: License :: OSI Approved :: MIT License
Classifier: Programming Language :: Python :: 3
Classifier: Programming Language :: Python :: 3.6
Classifier: Programming Language :: Python :: 3.7
Classifier: Programming Language :: Python :: 3.8
Classifier: Programming Language :: Python :: 3.9
Requires-Dist: matplotlib (>=3.3.3,<4.0.0)
Requires-Dist: numpy (>=1.19.5,<2.0.0)
Requires-Dist: toml (>=0.10.2,<0.11.0)
Project-URL: Documentation, https://a-lab-nagoya.github.io/custom-colormaps/
